asyncirc/__init__.py
asyncirc/_version.py
asyncirc/protocol.py
asyncirc/py.typed
asyncirc/server.py
asyncirc/util/__init__.py
asyncirc/util/backoff.py
async_irc-0.3.0.dist-info/METADATA
async_irc-0.3.0.dist-info/WHEEL
async_irc-0.3.0.dist-info/licenses/LICENSE
async_irc-0.3.0.dist-info/RECORD
