Metadata-Version: 2.4
Name: async-irc
Version: 0.3.0
Summary: A simple asyncio.Protocol implementation designed for IRC
Project-URL: Homepage, https://github.com/TotallyNotRobots/async-irc
Author-email: linuxdaemon <linuxdaemon.irc@gmail.com>
License-Expression: MIT
License-File: LICENSE
Keywords: async-irc,asyncio,asyncirc,irc,irc-framework
Classifier: Development Status :: 3 - Alpha
Classifier: License :: OSI Approved :: MIT License
Classifier: Programming Language :: Python :: 3 :: Only
Classifier: Programming Language :: Python :: 3.10
Classifier: Programming Language :: Python :: 3.11
Classifier: Programming Language :: Python :: 3.12
Classifier: Programming Language :: Python :: 3.13
Classifier: Programming Language :: Python :: 3.14
Requires-Python: >=3.10
Requires-Dist: py-irclib>=0.8.0
Requires-Dist: typing-extensions
